pace2024_verifier/__init__.py
pace2024_verifier/__main__.py
pace2024_verifier/cli.py
pace2024_verifier/pace.py
pace2024_verifier/tiny_test_set/instances/complete_4_5.gr
pace2024_verifier/tiny_test_set/instances/cycle_8_shuffled.gr
pace2024_verifier/tiny_test_set/instances/cycle_8_sorted.gr
pace2024_verifier/tiny_test_set/instances/grid_9_shuffled.gr
pace2024_verifier/tiny_test_set/instances/ladder_4_4_shuffled.gr
pace2024_verifier/tiny_test_set/instances/ladder_4_4_sorted.gr
pace2024_verifier/tiny_test_set/instances/matching_4_4.gr
pace2024_verifier/tiny_test_set/instances/path_9_shuffled.gr
pace2024_verifier/tiny_test_set/instances/path_9_sorted.gr
pace2024_verifier/tiny_test_set/instances/plane_5_6.gr
pace2024_verifier/tiny_test_set/instances/star_6.gr
pace2024_verifier/tiny_test_set/instances/tree_6_10.gr
pace2024_verifier/tiny_test_set/instances/website_20.gr
pace2024_verifier/tiny_test_set/solutions/complete_4_5.sol
pace2024_verifier/tiny_test_set/solutions/cycle_8_shuffled.sol
pace2024_verifier/tiny_test_set/solutions/cycle_8_sorted.sol
pace2024_verifier/tiny_test_set/solutions/grid_9_shuffled.sol
pace2024_verifier/tiny_test_set/solutions/ladder_4_4_shuffled.sol
pace2024_verifier/tiny_test_set/solutions/ladder_4_4_sorted.sol
pace2024_verifier/tiny_test_set/solutions/matching_4_4.sol
pace2024_verifier/tiny_test_set/solutions/path_9_shuffled.sol
pace2024_verifier/tiny_test_set/solutions/path_9_sorted.sol
pace2024_verifier/tiny_test_set/solutions/plane_5_6.sol
pace2024_verifier/tiny_test_set/solutions/star_6.sol
pace2024_verifier/tiny_test_set/solutions/tree_6_10.sol
pace2024_verifier/tiny_test_set/solutions/website_20.sol
pace2024_verifier/visualzier.py
pace2024_verifier-0.3.8.dist-info/LICENSE
pace2024_verifier-0.3.8.dist-info/METADATA
pace2024_verifier-0.3.8.dist-info/WHEEL
pace2024_verifier-0.3.8.dist-info/entry_points.txt
pace2024_verifier-0.3.8.dist-info/RECORD
