Metadata-Version: 2.1
Name: pace2024-verifier
Version: 0.3.8
Summary: 
Author: fabian
Author-email: fmklute@gmail.com
Requires-Python: >=3.9,<3.13
Classifier: Programming Language :: Python :: 3
Classifier: Programming Language :: Python :: 3.9
Classifier: Programming Language :: Python :: 3.10
Classifier: Programming Language :: Python :: 3.11
Classifier: Programming Language :: Python :: 3.12
Requires-Dist: click (>=8.1.7,<9.0.0)
Requires-Dist: networkx (>=3.2.1,<4.0.0)
Requires-Dist: numpy (>=1.26.1,<2.0.0)
Requires-Dist: pytest (>=7.4.3,<8.0.0)
Requires-Dist: segment-tree (>=0.3.2,<0.4.0)
